{
  "hash": "d5de003d",
  "configHash": "97b71450",
  "lockfileHash": "c0de9e24",
  "browserHash": "1fc5ecc0",
  "optimized": {
    "react": {
      "src": "../../node_modules/react/index.js",
      "file": "react.js",
      "fileHash": "6522cb72",
      "needsInterop": true
    },
    "react-dom/client": {
      "src": "../../node_modules/react-dom/client.js",
      "file": "react-dom_client.js",
      "fileHash": "bfc8db8b",
      "needsInterop": true
    },
    "react-router-dom": {
      "src": "../../node_modules/react-router-dom/dist/index.js",
      "file": "react-router-dom.js",
      "fileHash": "edb1c037",
      "needsInterop": false
    },
    "bootstrap/dist/js/bootstrap.bundle.min": {
      "src": "../../node_modules/bootstrap/dist/js/bootstrap.bundle.min.js",
      "file": "bootstrap_dist_js_bootstrap__bundle__min.js",
      "fileHash": "dee1cc8f",
      "needsInterop": true
    },
    "react-bootstrap": {
      "src": "../../node_modules/react-bootstrap/esm/index.js",
      "file": "react-bootstrap.js",
      "fileHash": "c723c7e8",
      "needsInterop": false
    },
    "swiper/modules": {
      "src": "../../node_modules/swiper/modules/index.mjs",
      "file": "swiper_modules.js",
      "fileHash": "c5230c33",
      "needsInterop": false
    },
    "swiper/react": {
      "src": "../../node_modules/swiper/swiper-react.mjs",
      "file": "swiper_react.js",
      "fileHash": "275f4e65",
      "needsInterop": false
    },
    "swiper": {
      "src": "../../node_modules/swiper/swiper.mjs",
      "file": "swiper.js",
      "fileHash": "a412e065",
      "needsInterop": false
    },
    "swiper/core": {
      "src": "../../node_modules/swiper/swiper.mjs",
      "file": "swiper_core.js",
      "fileHash": "b2112c86",
      "needsInterop": false
    }
  },
  "chunks": {
    "chunk-4ASWBRZ3": {
      "file": "chunk-4ASWBRZ3.js"
    },
    "chunk-O6O4HUXW": {
      "file": "chunk-O6O4HUXW.js"
    },
    "chunk-I6AGEYHY": {
      "file": "chunk-I6AGEYHY.js"
    },
    "chunk-ZHRMRTC2": {
      "file": "chunk-ZHRMRTC2.js"
    },
    "chunk-2JSOXIYZ": {
      "file": "chunk-2JSOXIYZ.js"
    },
    "chunk-LQ2VYIYD": {
      "file": "chunk-LQ2VYIYD.js"
    }
  }
}